filelambda/__init__.py
filelambda/files.py
filelambda-0.5.dist-info/LICENSE
filelambda-0.5.dist-info/METADATA
filelambda-0.5.dist-info/WHEEL
filelambda-0.5.dist-info/top_level.txt
filelambda-0.5.dist-info/RECORD
