Metadata-Version: 2.1
Name: filelambda
Version: 0.5
Summary: Functions for working with files in Python
Home-page: http://github.com/davidvhill/filelambda
Author: David V. Hill
Author-email: davehill75@gmail.com
License: MIT
Keywords: python files functional
Platform: UNKNOWN
Classifier: Development Status :: 4 - Beta
Classifier: License :: OSI Approved :: MIT License
Classifier: Programming Language :: Python :: 3
Provides-Extra: dev
Requires-Dist: twine ; extra == 'dev'
Provides-Extra: test
Requires-Dist: pytest ; extra == 'test'
